pokeapi_package/__init__.py
pokeapi_package/abilities.py
pokeapi_package/moves.py
pokeapi_package/pokemon.py
pokeapi_package/utils.py
pokepy/__init__.py
pokepy/abilities.py
pokepy/moves.py
pokepy/pokemon.py
pokepy/utils.py
Pokemon_Py-0.12.dist-info/METADATA
Pokemon_Py-0.12.dist-info/WHEEL
Pokemon_Py-0.12.dist-info/top_level.txt
Pokemon_Py-0.12.dist-info/RECORD
