Metadata-Version: 2.1
Name: Pokemon-Py
Version: 0.12
Summary: A Python wrapper for PokeAPI (https://pokeapi.co/)
Home-page: 
Author: Rick Verbon
Author-email: rick89@gmail.com
Classifier: Development Status :: 3 - Alpha
Classifier: Intended Audience :: Developers
Classifier: License :: OSI Approved :: MIT License
Classifier: Programming Language :: Python :: 3
Classifier: Programming Language :: Python :: 3.6
Classifier: Programming Language :: Python :: 3.7
Classifier: Programming Language :: Python :: 3.8
Classifier: Programming Language :: Python :: 3.9
Requires-Dist: requests
